Metadata-Version: 1.0
Name: scrapy-rabbitmq-scheduler-neo
Version: 1.0.6
Summary: Rabbitmq for Distributed scraping, copy from scrapy-rabbitmq-scheduler and fix some bugs
Home-page: https://github.com/aox-lei/scrapy-rabbitmq-scheduler
Author: aox lei
Author-email: 2387813033@qq.com
License: MIT
Platform: UNKNOWN
